concurrentor/__init__.py
concurrentor/py.typed
concurrentor-0.1.1.dist-info/METADATA
concurrentor-0.1.1.dist-info/WHEEL
concurrentor-0.1.1.dist-info/RECORD
