Metadata-Version: 2.4
Name: concurrentor
Version: 0.1.1
Summary: A simple wrapper class around anyio to help create programs that contain multiple concurrent but interacting parts.
Author-email: Shengchen Zhang <hello@shengchen.io>
Requires-Python: >=3.10
Requires-Dist: anyio>=4.12.0
